blockertest/main.py
blockertest-0.1.0.dist-info/METADATA
blockertest-0.1.0.dist-info/WHEEL
blockertest-0.1.0.dist-info/entry_points.txt
blockertest-0.1.0.dist-info/RECORD
