Metadata-Version: 2.1
Name: blockertest
Version: 0.1.0
Summary: 
Author: Alaqrakhadija
Author-email: alaqrakhadija@gmail.com
Requires-Python: >=3.9,<4.0
Classifier: Programming Language :: Python :: 3
Classifier: Programming Language :: Python :: 3.9
Classifier: Programming Language :: Python :: 3.10
Classifier: Programming Language :: Python :: 3.11
Requires-Dist: typer[all] (>=0.7.0,<0.8.0)
